impro/__init__.py
impro/intelligence.py
impro/monte_carlo.py
impro/under_development.py
impro-0.0.6.dist-info/LICENSE
impro-0.0.6.dist-info/LICENSE.rst
impro-0.0.6.dist-info/METADATA
impro-0.0.6.dist-info/WHEEL
impro-0.0.6.dist-info/entry_points.txt
impro-0.0.6.dist-info/top_level.txt
impro-0.0.6.dist-info/RECORD
