Metadata-Version: 2.1
Name: impro
Version: 0.0.6
Summary: Image Processing Functions
Author-email: Marlon Rodrigues Garcia <marlon.garcia@unesp.br>
License: MIT License
Project-URL: Homepage, https://github.com/MarlonGarcia/impro
Keywords: image processing,digital image,image functions
Classifier: License :: OSI Approved :: MIT License
Classifier: Programming Language :: Python
Classifier: Programming Language :: Python :: 3
Requires-Python: >=3.7
License-File: LICENSE
License-File: LICENSE.rst
Requires-Dist: numpy
Requires-Dist: opencv-contrib-python
Requires-Dist: matplotlib
Requires-Dist: imfun
Requires-Dist: scikit-learn
Requires-Dist: tqdm
Requires-Dist: pillow-heif
Requires-Dist: pmcx
